beginner/__init__.py
beginner/program.py
beginner/web.py
beginner-0.0.5.dist-info/LICENSE
beginner-0.0.5.dist-info/METADATA
beginner-0.0.5.dist-info/WHEEL
beginner-0.0.5.dist-info/top_level.txt
beginner-0.0.5.dist-info/RECORD
