Metadata-Version: 2.1
Name: beginner
Version: 0.0.5
Summary: Python package to let beginners in Python studies more easily.
Home-page: https://github.com/Dreambuilder4028/coder/
Author: Dreambuilder4028
Author-email: jiade_student@163.com
License: UNKNOWN
Platform: UNKNOWN
Classifier: Programming Language :: Python :: 3
Classifier: Operating System :: OS Independent
